lifeweeks/__init__.py
lifeweeks/cli.py
lifeweeks/plot.py
lifeweeks/utils.py
lifeweeks-0.1.3.dist-info/METADATA
lifeweeks-0.1.3.dist-info/WHEEL
lifeweeks-0.1.3.dist-info/entry_points.txt
lifeweeks-0.1.3.dist-info/RECORD
